huaweicloudsdkmoderation/__init__.py
huaweicloudsdkmoderation/v3/__init__.py
huaweicloudsdkmoderation/v3/moderation_async_client.py
huaweicloudsdkmoderation/v3/moderation_client.py
huaweicloudsdkmoderation/v3/model/__init__.py
huaweicloudsdkmoderation/v3/model/audio_create_request.py
huaweicloudsdkmoderation/v3/model/audio_input_body.py
huaweicloudsdkmoderation/v3/model/audio_moderation_result_detail.py
huaweicloudsdkmoderation/v3/model/audio_moderation_result_request_params.py
huaweicloudsdkmoderation/v3/model/audio_moderation_result_request_params_data.py
huaweicloudsdkmoderation/v3/model/audio_moderation_result_result.py
huaweicloudsdkmoderation/v3/model/batch_check_image_sync_request.py
huaweicloudsdkmoderation/v3/model/batch_check_image_sync_response.py
huaweicloudsdkmoderation/v3/model/check_image_moderation_request.py
huaweicloudsdkmoderation/v3/model/check_image_moderation_response.py
huaweicloudsdkmoderation/v3/model/face_location_detail.py
huaweicloudsdkmoderation/v3/model/image_batch_sync_detection_result.py
huaweicloudsdkmoderation/v3/model/image_batch_sync_req.py
huaweicloudsdkmoderation/v3/model/image_batch_sync_req_image_text_config.py
huaweicloudsdkmoderation/v3/model/image_batch_sync_req_urls.py
huaweicloudsdkmoderation/v3/model/image_detection_req.py
huaweicloudsdkmoderation/v3/model/image_detection_result.py
huaweicloudsdkmoderation/v3/model/image_detection_result_detail.py
huaweicloudsdkmoderation/v3/model/img_text_config.py
huaweicloudsdkmoderation/v3/model/ocr_text_detail.py
huaweicloudsdkmoderation/v3/model/qr_location_detail.py
huaweicloudsdkmoderation/v3/model/run_create_audio_moderation_job_request.py
huaweicloudsdkmoderation/v3/model/run_create_audio_moderation_job_response.py
huaweicloudsdkmoderation/v3/model/run_create_video_moderation_job_request.py
huaweicloudsdkmoderation/v3/model/run_create_video_moderation_job_response.py
huaweicloudsdkmoderation/v3/model/run_query_audio_moderation_job_request.py
huaweicloudsdkmoderation-3.1.184.dist-info/METADATA
huaweicloudsdkmoderation-3.1.184.dist-info/WHEEL
huaweicloudsdkmoderation-3.1.184.dist-info/licenses/LICENSE
huaweicloudsdkmoderation-3.1.184.dist-info/RECORD
